generatekey/__init__.py
generatekey/core.py
generatekey-0.1.1.dist-info/LICENSE
generatekey-0.1.1.dist-info/METADATA
generatekey-0.1.1.dist-info/WHEEL
generatekey-0.1.1.dist-info/entry_points.txt
generatekey-0.1.1.dist-info/RECORD
