Metadata-Version: 2.1
Name: generatekey
Version: 0.1.1
Summary: key generator
License: MIT
Author: Manuel Pita
Author-email: mpita1984@gmail.com
Requires-Python: >=3.10,<4.0
Classifier: License :: OSI Approved :: MIT License
Classifier: Programming Language :: Python :: 3
Classifier: Programming Language :: Python :: 3.10
Classifier: Programming Language :: Python :: 3.11
Classifier: Programming Language :: Python :: 3.12
Classifier: Programming Language :: Python :: 3.13
